{
    "display": {
        "icon": {
            "id": "minecraft:music_disc_far",
            "components": {
                "minecraft:item_model": "bcrmc6:music_disc_rain"
            }
        },
        "title": "It's Raining Somewhere Else",
        "description": "Crafted the \"It's Raining Somewhere Else\" music disc",
        "show_toast": true,
        "announce_to_chat": false,
        "hidden": true
    },
    "parent": "bcrmc6:root_discs",
    "criteria": {
        "requirement": {
            "trigger": "minecraft:recipe_unlocked",
            "conditions": {
                "recipe": "bcrmc6:music_disc_rain"
            }
        }
    }
}